nbpretty/__init__.py
nbpretty/preprocessors.py
nbpretty/templates/nbpretty/conf.json
nbpretty/templates/nbpretty/index.html.j2
nbpretty/templates/nbpretty/static/custom.css
nbpretty/toc.py
nbpretty/utils.py
nbpretty-0.3.3.dist-info/LICENSE
nbpretty-0.3.3.dist-info/METADATA
nbpretty-0.3.3.dist-info/WHEEL
nbpretty-0.3.3.dist-info/entry_points.txt
nbpretty-0.3.3.dist-info/RECORD
